[
	{
		"id": 186,
		"point_a": [
			-1600.0,
			-2816.0,
			1536.03125
		],
		"point_b": [
			-1344.01123,
			-2561.211914,
			1664.03125
		],
		"track": 1,
		"type": "start"
	},
	{
		"id": 187,
		"point_a": [
			-4096.0,
			-335.023742,
			576.03125
		],
		"point_b": [
			-3968.01123,
			192.0,
			704.03125
		],
		"track": 1,
		"type": "end"
	},
	{
		"id": 1285,
		"point_a": [
			-12336.0,
			3616.0,
			1.03125
		],
		"point_b": [
			-11984.0,
			3808.0,
			129.03125
		],
		"track": 0,
		"type": "end"
	},
	{
		"id": 1354,
		"point_a": [
			-3967.023681,
			-255.96875,
			128.03125
		],
		"point_b": [
			-3711.900146,
			127.96875,
			256.03125
		],
		"track": 0,
		"type": "start"
	}
]