[
	{
		"id": 4390,
		"point_a": [
			-4863.96875,
			-6311.085937,
			-1375.96875
		],
		"point_b": [
			-4416.03125,
			-6080.377929,
			-1247.96875
		],
		"track": 0,
		"type": "start"
	},
	{
		"id": 4391,
		"point_a": [
			8160.239257,
			4784.03125,
			657.03125
		],
		"point_b": [
			8319.96875,
			5647.96875,
			785.03125
		],
		"track": 0,
		"type": "end"
	},
	{
		"id": 4392,
		"point_a": [
			7480.0,
			5733.0,
			657.03125
		],
		"point_b": [
			7821.0,
			5908.0,
			785.03125
		],
		"track": 1,
		"type": "start"
	},
	{
		"id": 4393,
		"point_a": [
			11450.0,
			5805.0,
			657.03125
		],
		"point_b": [
			11792.0,
			5981.0,
			785.03125
		],
		"track": 1,
		"type": "end"
	}
]