[
	{
		"id": 1668449982,
		"point_a": [
			-1155.0,
			-10573.0,
			5154.03125
		],
		"point_b": [
			-898.0,
			-9973.0,
			5282.03125
		],
		"track": 0,
		"type": "end"
	},
	{
		"id": 1668449982,
		"point_a": [
			-723.0,
			7338.0,
			-4564.956542
		],
		"point_b": [
			-580.008361,
			7884.638183,
			-4436.956542
		],
		"track": 0,
		"type": "start"
	},
	{
		"id": 1668449982,
		"point_a": [
			-4678.0,
			-8385.0,
			3960.03125
		],
		"point_b": [
			-4182.0,
			-7837.0,
			4088.03125
		],
		"track": 1,
		"type": "end"
	},
	{
		"id": 1668449982,
		"point_a": [
			-2652.0,
			-10573.0,
			4813.03125
		],
		"point_b": [
			-2392.0,
			-9973.0,
			4941.03125
		],
		"track": 1,
		"type": "start"
	}
]