[
	{
		"id": 111,
		"point_a": [
			-256.0,
			-32.0,
			129.031
		],
		"point_b": [
			-80.0,
			144.0,
			256.031
		],
		"track": 0,
		"type": "start"
	},
	{
		"id": 112,
		"point_a": [
			1616.0,
			-8816.0,
			1121.03
		],
		"point_b": [
			1872.0,
			-8576.0,
			1248.03
		],
		"track": 0,
		"type": "end"
	},
	{
		"id": 113,
		"point_a": [
			2336.0,
			-240.0,
			417.026
		],
		"point_b": [
			2496.0,
			0.0,
			544.026
		],
		"track": 1,
		"type": "start"
	},
	{
		"id": 114,
		"point_a": [
			3600.0,
			-1952.0,
			-2398.97
		],
		"point_b": [
			3824.0,
			-1744.0,
			-2271.97
		],
		"track": 1,
		"type": "end"
	}
]