[
	{
		"id": 1668449982,
		"point_a": [
			3050.0,
			1643.0,
			-262.968
		],
		"point_b": [
			3820.0,
			1943.0,
			-135.968
		],
		"track": 0,
		"type": "end"
	},
	{
		"id": 1668449982,
		"point_a": [
			-512.0,
			-416.0,
			65.031
		],
		"point_b": [
			0.0,
			-260.0,
			192.031
		],
		"track": 0,
		"type": "start"
	},
	{
		"id": 1668449982,
		"point_a": [
			6122.0,
			6981.0,
			-114.968
		],
		"point_b": [
			6278.0,
			7531.0,
			12.031
		],
		"track": 1,
		"type": "end"
	},
	{
		"id": 1668449982,
		"point_a": [
			3488.0,
			6981.0,
			-114.968
		],
		"point_b": [
			3809.0,
			7531.0,
			12.031
		],
		"track": 1,
		"type": "start"
	},
	{
		"id": 1668449982,
		"point_a": [
			-512.0,
			6776.0,
			-543.968
		],
		"point_b": [
			-168.0,
			6884.0,
			-416.968
		],
		"track": 2,
		"type": "end"
	},
	{
		"id": 1668449982,
		"point_a": [
			-900.0,
			6780.0,
			-543.968
		],
		"point_b": [
			-556.0,
			6884.0,
			-416.968
		],
		"track": 2,
		"type": "start"
	}
]