[
	{
		"id": 1668471088,
		"point_a": [
			-1817.0,
			-10573.0,
			5155.03
		],
		"point_b": [
			-898.0,
			-9973.0,
			5282.03
		],
		"track": 0,
		"type": "end"
	},
	{
		"id": 1668471088,
		"point_a": [
			-723.0,
			7337.0,
			-4563.97
		],
		"point_b": [
			-581.0,
			7885.0,
			-4436.65
		],
		"track": 0,
		"type": "start"
	},
	{
		"id": 1668471088,
		"point_a": [
			-4678.0,
			-8385.0,
			3961.03
		],
		"point_b": [
			-4183.0,
			-7837.0,
			4088.03
		],
		"track": 1,
		"type": "end"
	},
	{
		"id": 1668471088,
		"point_a": [
			-156.0,
			-8384.0,
			3959.03
		],
		"point_b": [
			198.0,
			-7836.0,
			4086.03
		],
		"track": 1,
		"type": "start"
	}
]