[
	{
		"id": 1668471088,
		"point_a": [
			-1088.0,
			832.0,
			233.031
		],
		"point_b": [
			-896.0,
			1024.0,
			352.031
		],
		"track": 0,
		"type": "end"
	},
	{
		"id": 1668471088,
		"point_a": [
			-536.0,
			-344.0,
			-42.9688
		],
		"point_b": [
			-320.0,
			-128.0,
			84.0312
		],
		"track": 0,
		"type": "start"
	},
	{
		"id": 1668471088,
		"point_a": [
			-5535.0,
			1281.0,
			-2272.47
		],
		"point_b": [
			-5343.0,
			1432.0,
			-2145.47
		],
		"track": 1,
		"type": "end"
	},
	{
		"id": 1668471088,
		"point_a": [
			-6384.0,
			-3440.0,
			2079.54
		],
		"point_b": [
			-6320.0,
			-3376.0,
			2206.54
		],
		"track": 1,
		"type": "start"
	}
]