[
	{
		"id": 1668449982,
		"point_a": [
			9056.0,
			12032.0,
			15027.03125
		],
		"point_b": [
			9664.0,
			13056.0,
			15800.0
		],
		"track": 0,
		"type": "end"
	},
	{
		"id": 1668449982,
		"point_a": [
			-6512.0,
			14224.0,
			-2463.96875
		],
		"point_b": [
			-6000.0,
			15184.0,
			-2335.96875
		],
		"track": 0,
		"type": "start"
	},
	{
		"id": 1668449982,
		"point_a": [
			12560.0,
			-1856.0,
			-584.96875
		],
		"point_b": [
			13008.0,
			-1536.0,
			-456.96875
		],
		"track": 1,
		"type": "end"
	},
	{
		"id": 1668449982,
		"point_a": [
			11728.0,
			384.0,
			-2056.96875
		],
		"point_b": [
			12048.0,
			704.0,
			-1928.96875
		],
		"track": 1,
		"type": "start"
	}
]